deduplication/__init__.py
deduplication/lsimhash.py
deduplication/nlp.py
deduplication/simhash.py
deduplication-0.0.3.dist-info/LICENSE
deduplication-0.0.3.dist-info/METADATA
deduplication-0.0.3.dist-info/WHEEL
deduplication-0.0.3.dist-info/top_level.txt
deduplication-0.0.3.dist-info/RECORD
