Metadata-Version: 2.1
Name: deduplication
Version: 0.0.3
Summary: Remove duplicate documents via popular algorithms such as SimHash, SpotSig, Shingling, etc.
Home-page: https://github.com/Marcnuth/deduplication
Author: Marcnuth
Author-email: hxianxian@gmail.com
License: Apache License 2.0
Platform: UNKNOWN
Classifier: Topic :: Scientific/Engineering :: Artificial Intelligence
Classifier: Topic :: Software Development :: Libraries
Classifier: Programming Language :: Python :: 3
Requires-Dist: spacy (>='2.1.4')
